scine_utilities/LICENSE.txt
scine_utilities/__init__.py
scine_utilities/libcore.so
scine_utilities/libutilsos.so
scine_utilities/scine_utilities.cpython-311-x86_64-linux-gnu.so
scine_utilities/utilsos.module.so
scine_utilities.libs/libboost_atomic-00e6ede8.so.1.78.0
scine_utilities.libs/libboost_filesystem-e9e1d9ac.so.1.78.0
scine_utilities.libs/libboost_system-c0fa27da.so.1.78.0
scine_utilities.libs/libgomp-e985bcbb.so.1.0.0
scine_utilities-10.1.0.dist-info/METADATA
scine_utilities-10.1.0.dist-info/WHEEL
scine_utilities-10.1.0.dist-info/top_level.txt
scine_utilities-10.1.0.dist-info/RECORD
