Metadata-Version: 2.4
Name: scine_utilities
Version: 10.1.0
Summary: Utilities used in all SCINE modules
Home-page: https://www.scine.ethz.ch
Author: ETH Zurich, Department of Chemistry and Applied Biosciences, Reiher Group
Author-email: scine@phys.chem.ethz.ch
Classifier: Programming Language :: Python
Classifier: Programming Language :: C++
Classifier: Development Status :: 5 - Production/Stable
Classifier: Intended Audience :: Science/Research
Classifier: License :: OSI Approved :: BSD License
Classifier: Natural Language :: English
Classifier: Topic :: Scientific/Engineering :: Chemistry
Requires-Dist: numpy
Requires-Dist: scipy
Dynamic: author
Dynamic: author-email
Dynamic: classifier
Dynamic: description
Dynamic: home-page
Dynamic: requires-dist
Dynamic: summary
